pybpod_gui_plugin_timeline-1.0.1.dist-info/METADATA
pybpod_gui_plugin_timeline-1.0.1.dist-info/RECORD
pybpod_gui_plugin_timeline-1.0.1.dist-info/WHEEL
pybpod_gui_plugin_timeline-1.0.1.dist-info/top_level.txt
pybpodgui_plugin_timeline/__init__.py
pybpodgui_plugin_timeline/settings.py
pybpodgui_plugin_timeline/trials_plot_window.py
pybpodgui_plugin_timeline/models/__init__.py
pybpodgui_plugin_timeline/models/session/__init__.py
pybpodgui_plugin_timeline/models/session/session_treenode.py
pybpodgui_plugin_timeline/resources/graph.png
