Metadata-Version: 2.1
Name: pybpod-gui-plugin-timeline
Version: 1.0.1
Summary: Trials plot plugin
Home-page: https://bitbucket.org/fchampalimaud/pycontrolgui
Author: Carlos Mão de Ferro, Ricardo Jorge Vieira Ribeiro
Author-email: cajomferro@gmail.com, ricardojvr@gmail.com
License: Copyright (C) 2007 Free Software Foundation, Inc. <http://fsf.org/>
Platform: UNKNOWN
